{"chunk_definitions":[{"chunk_id":"csetup_chunk","chunk_label":"setup","document_id":"3252D1AE","expansion_state":0,"options":{"engine":"r","include":false,"label":"setup"},"row":12,"row_count":1,"visible":true},{"chunk_id":"ckzxppklb7o12","chunk_label":"unnamed-chunk-1","document_id":"3252D1AE","expansion_state":0,"options":{"engine":"r","include":false,"label":"unnamed-chunk-243"},"row":48,"row_count":1,"visible":true},{"chunk_id":"cnqcm6w2nazw0","chunk_label":"unnamed-chunk-2","document_id":"3252D1AE","expansion_state":0,"options":{"echo":true,"engine":"r","label":"unnamed-chunk-244"},"row":61,"row_count":1,"visible":true},{"chunk_id":"cofhmmewncmsf","chunk_label":"unnamed-chunk-3","document_id":"3252D1AE","expansion_state":0,"options":{"echo":true,"engine":"r","label":"unnamed-chunk-245"},"row":67,"row_count":1,"visible":true},{"chunk_id":"cemvo55vqkgav","chunk_label":"unnamed-chunk-4","document_id":"3252D1AE","expansion_state":0,"options":{"echo":true,"engine":"r","label":"unnamed-chunk-246"},"row":81,"row_count":1,"visible":true},{"chunk_id":"crl32ppmnwedh","chunk_label":"unnamed-chunk-5","document_id":"3252D1AE","expansion_state":0,"options":{"echo":true,"engine":"r","label":"unnamed-chunk-247"},"row":109,"row_count":1,"visible":true},{"chunk_id":"cqz1vbr71k9zh","chunk_label":"unnamed-chunk-6","document_id":"3252D1AE","expansion_state":0,"options":{"echo":true,"engine":"r","label":"unnamed-chunk-248"},"row":116,"row_count":1,"visible":true},{"chunk_id":"cs6trhjdbyr0q","chunk_label":"unnamed-chunk-7","document_id":"3252D1AE","expansion_state":0,"options":{"echo":true,"engine":"r","label":"unnamed-chunk-249"},"row":147,"row_count":1,"visible":true},{"chunk_id":"c93feoadvny9o","chunk_label":"unnamed-chunk-8","document_id":"3252D1AE","expansion_state":0,"options":{"echo":true,"engine":"r","label":"unnamed-chunk-250"},"row":157,"row_count":1,"visible":true},{"chunk_id":"coeu5lqqz844n","chunk_label":"unnamed-chunk-9","document_id":"3252D1AE","expansion_state":0,"options":{"echo":true,"engine":"r","label":"unnamed-chunk-251"},"row":165,"row_count":1,"visible":true},{"chunk_id":"ccjoesknnr0s4","chunk_label":"unnamed-chunk-10","document_id":"3252D1AE","expansion_state":0,"options":{"echo":true,"engine":"r","label":"unnamed-chunk-252"},"row":181,"row_count":1,"visible":true},{"chunk_id":"csjzf8x7ga677","chunk_label":"unnamed-chunk-11","document_id":"3252D1AE","expansion_state":0,"options":{"engine":"r","label":"unnamed-chunk-253"},"row":189,"row_count":1,"visible":true},{"chunk_id":"c9qj11l43v1hz","chunk_label":"unnamed-chunk-12","document_id":"3252D1AE","expansion_state":0,"options":{"engine":"r","label":"unnamed-chunk-254"},"row":197,"row_count":1,"visible":true},{"chunk_id":"cnawzonjbh1vc","chunk_label":"unnamed-chunk-13","document_id":"3252D1AE","expansion_state":0,"options":{"engine":"r","label":"unnamed-chunk-255"},"row":206,"row_count":1,"visible":true},{"chunk_id":"cykd2c7w1nty6","chunk_label":"unnamed-chunk-14","document_id":"3252D1AE","expansion_state":0,"options":{"engine":"r","label":"unnamed-chunk-260"},"row":215,"row_count":1,"visible":true}],"default_chunk_options":{"echo":true},"doc_write_time":1587443637,"working_dir":null}